{
  "project_info": {
    "project_number": "878124439236",
    "project_id": "safecampus-hackathon-2025",
    "storage_bucket": "safecampus-hackathon-2025.firebasestorage.app"
  },
  "client": [
    {
      "client_info": {
        "mobilesdk_app_id": "1:878124439236:android:f055f73f1af6fe0a661b91",
        "android_client_info": {
          "package_name": "com.example.safe_campus"
        }
      },
      "oauth_client": [],
      "api_key": [
        {
          "current_key": "AIzaSyD1QX8A4UMnK6NYPjaxomQWGwzNacv5eks"
        }
      ],
      "services": {
        "appinvite_service": {
          "other_platform_oauth_client": []
        }
      }
    }
  ],
  "configuration_version": "1"
}